wtslog/Logger.py
wtslog/__init__.py
wtslog-0.4.0.dist-info/LICENSE
wtslog-0.4.0.dist-info/METADATA
wtslog-0.4.0.dist-info/WHEEL
wtslog-0.4.0.dist-info/top_level.txt
wtslog-0.4.0.dist-info/RECORD
