Metadata-Version: 2.1
Name: wtslog
Version: 0.4.0
Summary: a Way Too Simple LOGger
Home-page: https://github.com/kiriDevs/wtslog
Author: kiriDevs
Author-email: author@example.com
License: UNKNOWN
Project-URL: Bug Tracker, https://github.com/kiriDevs/wtslog/issues
Platform: UNKNOWN
Classifier: Programming Language :: Python :: 3
Classifier: License :: OSI Approved :: ISC License (ISCL)
Classifier: Operating System :: OS Independent
Requires-Python: >=3.6
License-File: LICENSE
